fytok/__init__.py
fytok/__version__.py
fytok/contexts/pulse_schedule.py
fytok/contexts/scenario.py
fytok/contexts/tokamak.py
fytok/mappings/cfetr/imas/3/static/config.xml
fytok/mappings/cfetr/imas/3/static/pf_active.xml
fytok/mappings/cfetr/imas/3/static/tf.xml
fytok/mappings/cfetr/imas/3/static/vessel.txt
fytok/mappings/cfetr/imas/3/static/wall.xml
fytok/mappings/cmod/imas/3/cmod.xml
fytok/mappings/d3d/imas/3/d3d.xml
fytok/mappings/east/imas/3/static/config.xml
fytok/mappings/east/imas/3/static/dataset_fair.xml
fytok/mappings/east/imas/3/static/dd_interferometer.xsd
fytok/mappings/east/imas/3/static/ec_launchers.xml
fytok/mappings/east/imas/3/static/ic_antenna.xml
fytok/mappings/east/imas/3/static/interferometer.xml
fytok/mappings/east/imas/3/static/lh_antenna.xml
fytok/mappings/east/imas/3/static/magnetics.xml
fytok/mappings/east/imas/3/static/magnetics_east.xml
fytok/mappings/east/imas/3/static/magnetics_pcs.xml
fytok/mappings/east/imas/3/static/nbi.xml
fytok/mappings/east/imas/3/static/pf_active.xml
fytok/mappings/east/imas/3/static/pf_active_yu.xml
fytok/mappings/east/imas/3/static/tf.xml
fytok/mappings/east/imas/3/static/wall.data
fytok/mappings/east/imas/3/static/wall.xml
fytok/mappings/iter/imas/3/static/config.xml
fytok/mappings/iter/imas/3/static/dataset_fair.xml
fytok/mappings/iter/imas/3/static/magnetics.xml
fytok/mappings/iter/imas/3/static/pf_active.xml
fytok/mappings/iter/imas/3/static/wall.xml
fytok/mappings/sparc/SPARC.svg
fytok/modules/amns_data.py
fytok/modules/core_profiles.py
fytok/modules/core_sources.py
fytok/modules/core_transport.py
fytok/modules/dataset_fair.py
fytok/modules/distribution_sources.py
fytok/modules/distributions.py
fytok/modules/ec_launchers.py
fytok/modules/edge_profiles.py
fytok/modules/edge_sources.py
fytok/modules/edge_transport.py
fytok/modules/equilibrium.py
fytok/modules/equilibrium_solver.py
fytok/modules/gyrokinetics.py
fytok/modules/ic_antennas.py
fytok/modules/interferometer.py
fytok/modules/lh_antennas.py
fytok-0.5.2.2.dist-info/LICENSE.txt
fytok-0.5.2.2.dist-info/METADATA
fytok-0.5.2.2.dist-info/WHEEL
fytok-0.5.2.2.dist-info/top_level.txt
fytok-0.5.2.2.dist-info/RECORD
